{
  "type": "FeatureCollection",
  "features": [
    {
      "type": "Feature",
      "geometry": {
        "type": "Point",
        "coordinates": [
          -0.1278,
          51.5074
        ]
      },
      "properties": {
        "name": "London",
        "population": 8982000
      }
    },
    {
      "type": "Feature",
      "geometry": {
        "type": "Point",
        "coordinates": [
          2.3522,
          48.8566
        ]
      },
      "properties": {
        "name": "Paris",
        "population": 2141000
      }
    },
    {
      "type": "Feature",
      "geometry": {
        "type": "Point",
        "coordinates": [
          -74.006,
          40.7128
        ]
      },
      "properties": {
        "name": "New York",
        "population": 8399000
      }
    }
  ]
}